NetkillerDatabaseFix1/README.md
NetkillerDatabaseFix1/__init__.py
NetkillerDatabaseFix1/__main__.py
NetkillerDatabaseFix1/file.epub
NetkillerDatabaseFix1/index.html
NetkillerDatabaseFix1/css/__init__.py
NetkillerDatabaseFix1/css/annotations.css
NetkillerDatabaseFix1/css/main.css
NetkillerDatabaseFix1/css/normalize.css
NetkillerDatabaseFix1/css/popup.css
NetkillerDatabaseFix1/font/__init__.py
NetkillerDatabaseFix1/font/fontello.eot
NetkillerDatabaseFix1/font/fontello.svg
NetkillerDatabaseFix1/font/fontello.ttf
NetkillerDatabaseFix1/font/fontello.woff
NetkillerDatabaseFix1/img/__init__.py
NetkillerDatabaseFix1/img/annotator-glyph-sprite.png
NetkillerDatabaseFix1/img/annotator-icon-sprite.png
NetkillerDatabaseFix1/img/apple-touch-icon.png
NetkillerDatabaseFix1/img/cancelfullscreen.png
NetkillerDatabaseFix1/img/close.png
NetkillerDatabaseFix1/img/fullscreen.png
NetkillerDatabaseFix1/img/loader.gif
NetkillerDatabaseFix1/img/menu-icon.png
NetkillerDatabaseFix1/img/save.png
NetkillerDatabaseFix1/img/saved.png
NetkillerDatabaseFix1/img/settings-s.png
NetkillerDatabaseFix1/img/settings.png
NetkillerDatabaseFix1/img/star.png
NetkillerDatabaseFix1/js/__init__.py
NetkillerDatabaseFix1/js/epub.js
NetkillerDatabaseFix1/js/epub.min.js
NetkillerDatabaseFix1/js/epub.min.map
NetkillerDatabaseFix1/js/hooks.min.js
NetkillerDatabaseFix1/js/hooks.min.map
NetkillerDatabaseFix1/js/reader.js
NetkillerDatabaseFix1/js/reader.js.map
NetkillerDatabaseFix1/js/reader.min.js
NetkillerDatabaseFix1/js/reader.min.map
NetkillerDatabaseFix1/js/hooks/__init__.py
NetkillerDatabaseFix1/js/hooks/extensions/__init__.py
NetkillerDatabaseFix1/js/hooks/extensions/highlight.js
NetkillerDatabaseFix1/js/libs/__init__.py
NetkillerDatabaseFix1/js/libs/jquery.min.js
NetkillerDatabaseFix1/js/libs/localforage.min.js
NetkillerDatabaseFix1/js/libs/screenfull.js
NetkillerDatabaseFix1/js/libs/screenfull.min.js
NetkillerDatabaseFix1/js/libs/zip.min.js
NetkillerDatabaseFix1/js/plugins/__init__.py
netkiller_database_fix1-2025.3.24.1.dist-info/METADATA
netkiller_database_fix1-2025.3.24.1.dist-info/WHEEL
netkiller_database_fix1-2025.3.24.1.dist-info/entry_points.txt
netkiller_database_fix1-2025.3.24.1.dist-info/top_level.txt
netkiller_database_fix1-2025.3.24.1.dist-info/RECORD
